{
  "date": "2025-10-21",
  "pangram": "fluidity",
  "letters": [ "i", "d", "f", "l", "t", "u", "y" ],
  "required": "i",
  "words": [
    "dill",
    "fill",
    "flit",
    "idly",
    "iffy",
    "lift",
    "lilt",
    "lily",
    "tidy",
    "tiff",
    "till",
    "tilt",
    "dilly",
    "ditty",
    "fifty",
    "filly",
    "fitly",
    "fluid",
    "idyll",
    "tutti",
    "diddly",
    "fiddly",
    "fitful",
    "fulfil",
    "tiddly",
    "tidily",
    "dutiful",
    "fluidly",
    "fulfill",
    "utility",
    "fitfully",
    "fluidity",
    "futility",
    "dutifully"
  ]
}