{
  "date": "2025-01-09",
  "clue": "Make a small addition, then it's even! (5)",
  "enumeration": "5",
  "answer": "SEVEN",
  "explanation": "Make a small (S) addition, then it's EVEN = SEVEN. Make a small addition (1) to SEVEN, then it's even!",
  "hints": [
    "\"Small\" can represent the letter S.",
    "The \"!\" in the clue is hinting that something unusual is going on.",
    "The whole clue gives you the wordplay, or read another way, the definition.",
    "A small addition (1) makes it even. So the answer itself must be odd."
  ]
}
