{
  "date": "2025-09-23",
  "title": "Tuesday Mini",
  "author": "Luna",
  "rows": [
    "BOLD#",
    "ASIA#",
    "RANTS",
    "#KEEL",
    "#ADDY"
  ],
  "clues": {
    "across": [
      {
        "row": 0,
        "col": 0,
        "clue": "Strong type"
      },
      {
        "row": 1,
        "col": 0,
        "clue": "Continent containing 2-down"
      },
      {
        "row": 2,
        "col": 0,
        "clue": "Partner for raves"
      },
      {
        "row": 3,
        "col": 1,
        "clue": "Ship's spine"
      },
      {
        "row": 4,
        "col": 1,
        "clue": "MSN address, back in the day?"
      }
    ],
    "down": [
      {
        "row": 0,
        "col": 0,
        "clue": "Tavern"
      },
      {
        "row": 0,
        "col": 1,
        "clue": "City found in 5-across"
      },
      {
        "row": 0,
        "col": 2,
        "clue": "Like paper in a notebook"
      },
      {
        "row": 0,
        "col": 3,
        "clue": "Behind the times"
      },
      {
        "row": 2,
        "col": 4,
        "clue": "Stallone, informally"
      }
    ]
  }
}